nomedia/__init__.py
nomedia/__main__.py
tests/__init__.py
tests/tests.py
NoMedia-1.0.2.dist-info/LICENSE
NoMedia-1.0.2.dist-info/METADATA
NoMedia-1.0.2.dist-info/WHEEL
NoMedia-1.0.2.dist-info/entry_points.txt
NoMedia-1.0.2.dist-info/top_level.txt
NoMedia-1.0.2.dist-info/RECORD
