Metadata-Version: 2.2
Name: NoMedia
Version: 1.0.2
Summary: Hides the indicated folders from the cell phone's media
Author-email: RuanMiguel-DRD <ruanmigueldrd@outlook.com>
License: Unlicense
Project-URL: Homepage, https://github.com/RuanMiguel-DRD/NoMedia
Project-URL: Source Code, https://github.com/RuanMiguel-DRD/NoMedia
Project-URL: Issue Tracker, https://github.com/RuanMiguel-DRD/NoMedia/issues
Classifier: Programming Language :: Python :: 3.6
Classifier: Development Status :: 5 - Production/Stable
Classifier: License :: OSI Approved :: The Unlicense (Unlicense)
Requires-Python: >=3.6
License-File: LICENSE
Provides-Extra: dev
Requires-Dist: build; extra == "dev"
Requires-Dist: twine; extra == "dev"
Requires-Dist: vermin; extra == "dev"
Requires-Dist: virtualenv; extra == "dev"
